lcurvetools/__init__.py
lcurvetools/lcurves.py
lcurvetools/utils.py
lcurvetools-1.1.0.dist-info/licenses/LICENSE
lcurvetools-1.1.0.dist-info/METADATA
lcurvetools-1.1.0.dist-info/WHEEL
lcurvetools-1.1.0.dist-info/top_level.txt
lcurvetools-1.1.0.dist-info/RECORD
