Metadata-Version: 2.4
Name: lcurvetools
Version: 1.1.0
Summary: Simple Python tools for plotting learning curves of neural network models trained with the Keras, Ultralytics YOLO or scikit-learn framework in a single figure in an easy-to-understand format.
Home-page: https://github.com/kamua/lcurvetools
Author: Andriy Konovalov
Author-email: kandriy74@gmail.com
License: BSD 3-Clause License
Keywords: learning curve,keras,ultralytics yolo,scikit-learn,loss_curve,validation_score
Classifier: Development Status :: 5 - Production/Stable
Classifier: License :: OSI Approved :: BSD License
Classifier: Intended Audience :: Science/Research
Classifier: Intended Audience :: Education
Classifier: Topic :: Scientific/Engineering
Classifier: Operating System :: Microsoft :: Windows
Classifier: Operating System :: POSIX
Classifier: Operating System :: Unix
Classifier: Operating System :: MacOS
Classifier: Programming Language :: Python :: 3
Classifier: Programming Language :: Python :: 3 :: Only
Requires-Python: >=3.10
License-File: LICENSE
Requires-Dist: numpy
Requires-Dist: matplotlib
Requires-Dist: scikit-learn
Dynamic: author
Dynamic: author-email
Dynamic: classifier
Dynamic: description
Dynamic: description-content-type
Dynamic: home-page
Dynamic: keywords
Dynamic: license
Dynamic: license-file
Dynamic: requires-dist
Dynamic: requires-python
Dynamic: summary
